[
  {
    "stats": [
      {
        "explanation": "Here is the backstory to this data.\nAnd this is a line break",
        "height": 300,
        "link": "/public/question/8910b979-baf2-47dc-a204-f28545c3877d",
        "title": "Testing",
        "width": 400
      }
    ],
    "title": "En bref"
  },
  {
    "stats": [
      {
        "explanation": "Here is the backstory to this data.\n\nAnd this is a new paragraph",
        "link": "/public/question/d548a194-a203-40d1-b43a-575db32f231e",
        "title": "Testing"
      }
    ],
    "title": "Mesure approvisonnement"
  }
]
